youtube_api/__init__.py
youtube_api/parsers.py
youtube_api/youtube_api.py
youtube_api/youtube_api_utils.py
youtube_data_api-0.0.21.dist-info/LICENSE
youtube_data_api-0.0.21.dist-info/METADATA
youtube_data_api-0.0.21.dist-info/WHEEL
youtube_data_api-0.0.21.dist-info/top_level.txt
youtube_data_api-0.0.21.dist-info/RECORD
