Metadata-Version: 2.1
Name: youtube-data-api
Version: 0.0.21
Summary: youtube-data-api is a Python wrapper for the YouTube Data API.
Home-page: https://github.com/mabrownnyu/youtube-data-api
Author: Leon Yin, Megan Brown
License: MIT
Keywords: youtube-data-api youtube-data youtube-api wrapper youtube tweepy social-media
Platform: UNKNOWN
Classifier: Programming Language :: Python :: 3
Classifier: License :: OSI Approved :: MIT License
Classifier: Operating System :: OS Independent
Requires-Dist: pandas
Requires-Dist: requests
